fast_autocomplete/__init__.py
fast_autocomplete/demo.py
fast_autocomplete/draw.py
fast_autocomplete/dwg.py
fast_autocomplete/lfucache.py
fast_autocomplete/loader.py
fast_autocomplete/misc.py
fast_autocomplete/normalize.py
fast_autocomplete-0.9.0.dist-info/AUTHORS
fast_autocomplete-0.9.0.dist-info/LICENSE
fast_autocomplete-0.9.0.dist-info/METADATA
fast_autocomplete-0.9.0.dist-info/WHEEL
fast_autocomplete-0.9.0.dist-info/top_level.txt
fast_autocomplete-0.9.0.dist-info/RECORD
