Metadata-Version: 2.1
Name: fast-autocomplete
Version: 0.9.0
Summary: Fast Autocomplete using Directed Word Graph
Home-page: https://github.com/seperman/fast-autocomplete
Author: Sep Dehpour
Author-email: sep@zepworks.com
License: MIT
Platform: UNKNOWN
Classifier: Intended Audience :: Developers
Classifier: Operating System :: OS Independent
Classifier: Topic :: Software Development
Classifier: Programming Language :: Python :: 3.6
Classifier: Programming Language :: Python :: 3.7
Classifier: Programming Language :: Python :: 3.8
Classifier: Programming Language :: Python :: 3.9
Classifier: Development Status :: 4 - Beta
Provides-Extra: levenshtein
Provides-Extra: pylev
License-File: LICENSE
License-File: AUTHORS
